hifieval.py
hifieval-0.4.0.dist-info/METADATA
hifieval-0.4.0.dist-info/WHEEL
hifieval-0.4.0.dist-info/licenses/LICENSE
hifieval-0.4.0.dist-info/RECORD
