Metadata-Version: 2.1
Name: hifieval
Version: 0.4.0
Summary: A tool to evaluate long-read error correction mainly with PacBio High-Fidelity Reads
Project-URL: Homepage, https://github.com/magspho/hifieval
Project-URL: Bug Tracker, https://github.com/magspho/hifieval/issues
Author-email: Yujie Guo <yguo@ds.dfci.harvard.edu>
License-File: LICENSE
Classifier: License :: OSI Approved :: MIT License
Classifier: Operating System :: OS Independent
Classifier: Programming Language :: Python :: 3
Requires-Python: >=3.5
